auxfun.py
clans.py
dectree.py
degais.py
ezGraph.py
palette.py
degais-1.4.dist-info/LICENSE
degais-1.4.dist-info/METADATA
degais-1.4.dist-info/WHEEL
degais-1.4.dist-info/entry_points.txt
degais-1.4.dist-info/top_level.txt
degais-1.4.dist-info/RECORD
