Metadata-Version: 2.1
Name: degais
Version: 1.4
Summary: Decomposing Gaifman Structures (again)
Author-email: José Luis Balcázar <jose.luis.balcazar@upc.edu>
Project-URL: Homepage, https://github.com/balqui/degais
Project-URL: Bug Tracker, https://github.com/balqui/degais/issues
Classifier: Programming Language :: Python :: 3
Classifier: License :: OSI Approved :: MIT License
Classifier: Operating System :: OS Independent
Requires-Python: >=3.12
License-File: LICENSE
Requires-Dist: graphviz >=0.20.3
